[
  {
    "received_at_kst": "2026-06-30T20:45:31.266434+09:00",
    "ws_url": "ws://ops.koreainvestment.com:21000",
    "msg_type": "ack",
    "tr_id": "H0MFCNT0",
    "parsed": {
      "header": {
        "tr_id": "H0MFCNT0",
        "tr_key": "A01606",
        "encrypt": "N"
      },
      "body": {
        "rt_cd": "0",
        "msg_cd": "OPSP0000",
        "msg1": "SUBSCRIBE SUCCESS",
        "output": {
          "iv": "849fc80a1a32c222",
          "key": "fjjlksfzaeptvqfslqbaeouoywvjzzte"
        }
      }
    }
  },
  {
    "received_at_kst": "2026-06-30T20:45:31.437957+09:00",
    "ws_url": "ws://ops.koreainvestment.com:21000",
    "msg_type": "ack",
    "tr_id": "H0MFCNT0",
    "parsed": {
      "header": {
        "tr_id": "H0MFCNT0",
        "tr_key": "A06606",
        "encrypt": "N"
      },
      "body": {
        "rt_cd": "0",
        "msg_cd": "OPSP0000",
        "msg1": "SUBSCRIBE SUCCESS",
        "output": {
          "iv": "849fc80a1a32c222",
          "key": "fjjlksfzaeptvqfslqbaeouoywvjzzte"
        }
      }
    }
  },
  {
    "received_at_kst": "2026-06-30T20:45:31.438031+09:00",
    "ws_url": "ws://ops.koreainvestment.com:21000",
    "msg_type": "ack",
    "tr_id": "H0MFASP0",
    "parsed": {
      "header": {
        "tr_id": "H0MFASP0",
        "tr_key": "A06606",
        "encrypt": "N"
      },
      "body": {
        "rt_cd": "0",
        "msg_cd": "OPSP0000",
        "msg1": "SUBSCRIBE SUCCESS",
        "output": {
          "iv": "849fc80a1a32c222",
          "key": "fjjlksfzaeptvqfslqbaeouoywvjzzte"
        }
      }
    }
  },
  {
    "received_at_kst": "2026-06-30T20:45:41.543887+09:00",
    "ws_url": "ws://ops.koreainvestment.com:21000",
    "msg_type": "ack",
    "tr_id": "PINGPONG",
    "parsed": {
      "header": {
        "tr_id": "PINGPONG",
        "datetime": "20260630204541"
      }
    }
  }
]