[
  {
    "received_at_kst": "2026-05-27T05:49:03.305620+09:00",
    "ws_url": "ws://ops.koreainvestment.com:21000",
    "msg_type": "ack",
    "tr_id": "H0MFCNT0",
    "parsed": {
      "header": {
        "tr_id": "H0MFCNT0",
        "tr_key": "A01606",
        "encrypt": "N"
      },
      "body": {
        "rt_cd": "0",
        "msg_cd": "OPSP0000",
        "msg1": "SUBSCRIBE SUCCESS",
        "output": {
          "iv": "a71d3e684af4d2d6",
          "key": "gzkefxhldmweklvotqqwhkyhruxfocpv"
        }
      }
    }
  },
  {
    "received_at_kst": "2026-05-27T05:49:03.515522+09:00",
    "ws_url": "ws://ops.koreainvestment.com:21000",
    "msg_type": "ack",
    "tr_id": "H0MFCNT0",
    "parsed": {
      "header": {
        "tr_id": "H0MFCNT0",
        "tr_key": "A06606",
        "encrypt": "N"
      },
      "body": {
        "rt_cd": "0",
        "msg_cd": "OPSP0000",
        "msg1": "SUBSCRIBE SUCCESS",
        "output": {
          "iv": "a71d3e684af4d2d6",
          "key": "gzkefxhldmweklvotqqwhkyhruxfocpv"
        }
      }
    }
  },
  {
    "received_at_kst": "2026-05-27T05:49:03.515605+09:00",
    "ws_url": "ws://ops.koreainvestment.com:21000",
    "msg_type": "ack",
    "tr_id": "H0MFASP0",
    "parsed": {
      "header": {
        "tr_id": "H0MFASP0",
        "tr_key": "A06606",
        "encrypt": "N"
      },
      "body": {
        "rt_cd": "0",
        "msg_cd": "OPSP0000",
        "msg1": "SUBSCRIBE SUCCESS",
        "output": {
          "iv": "a71d3e684af4d2d6",
          "key": "gzkefxhldmweklvotqqwhkyhruxfocpv"
        }
      }
    }
  },
  {
    "received_at_kst": "2026-05-27T05:49:07.515798+09:00",
    "ws_url": "ws://ops.koreainvestment.com:21000",
    "msg_type": "trade",
    "tr_id": "H0MFCNT0",
    "symbol": "A01606",
    "parsed": {
      "FUTS_SHRN_ISCD": "A01606",
      "BSOP_HOUR": "054907",
      "FUTS_PRDY_VRSS": "56.45",
      "PRDY_VRSS_SIGN": "2",
      "FUTS_PRDY_CTRT": "4.45",
      "FUTS_PRPR": "1323.85",
      "FUTS_OPRC": "1268.20",
      "FUTS_HGPR": "1327.45",
      "FUTS_LWPR": "1267.00",
      "LAST_CNQN": "1",
      "ACML_VOL": "27221",
      "ACML_TR_PBMN": "8842655237",
      "HTS_THPR": "1260.53",
      "MRKT_BASIS": "63.32",
      "DPRT": "5.02",
      "NMSC_FCTN_STPL_PRC": "0.00",
      "FMSC_FCTN_STPL_PRC": "0.00",
      "SPEAD_PRC": "3.60",
      "HTS_OTST_STPL_QTY": "195269",
      "OTST_STPL_QTY_ICDC": "-276",
      "OPRC_HOUR": "000000",
      "OPRC_VRSS_PRPR_SIGN": "2",
      "OPRC_VRSS_NMIX_PRPR": "55.65",
      "HGPR_HOUR": "000000",
      "HGPR_VRSS_PRPR_SIGN": "5",
      "HGPR_VRSS_NMIX_PRPR": "-3.60",
      "LWPR_HOUR": "000000",
      "LWPR_VRSS_PRPR_SIGN": "2",
      "LWPR_VRSS_NMIX_PRPR": "56.85",
      "SHNU_RATE": "0.51",
      "CTTR": "103.62",
      "ESDG": "63.32",
      "OTST_STPL_RGBF_QTY_ICDC": "0",
      "THPR_BASIS": "0.00",
      "FUTS_ASKP1": "1324.25",
      "FUTS_BIDP1": "1323.45",
      "ASKP_RSQN1": "4",
      "BIDP_RSQN1": "1",
      "SELN_CNTG_CSNU": "11268",
      "SHNU_CNTG_CSNU": "10888",
      "NTBY_CNTG_CSNU": "-380",
      "SELN_CNTG_SMTN": "13360",
      "SHNU_CNTG_SMTN": "13843",
      "TOTAL_ASKP_RSQN": "324",
      "TOTAL_BIDP_RSQN": "1003",
      "PRDY_VOL_VRSS_ACML_VOL_RATE": "176.40",
      "DYNM_MXPR": "1349.15",
      "DYNM_LLAM": "1298.55",
      "DYNM_PRC_LIMT_YN": "2"
    }
  },
  {
    "received_at_kst": "2026-05-27T05:49:14.776337+09:00",
    "ws_url": "ws://ops.koreainvestment.com:21000",
    "msg_type": "trade",
    "tr_id": "H0MFCNT0",
    "symbol": "A01606",
    "parsed": {
      "FUTS_SHRN_ISCD": "A01606",
      "BSOP_HOUR": "054914",
      "FUTS_PRDY_VRSS": "56.45",
      "PRDY_VRSS_SIGN": "2",
      "FUTS_PRDY_CTRT": "4.45",
      "FUTS_PRPR": "1323.85",
      "FUTS_OPRC": "1268.20",
      "FUTS_HGPR": "1327.45",
      "FUTS_LWPR": "1267.00",
      "LAST_CNQN": "1",
      "ACML_VOL": "27222",
      "ACML_TR_PBMN": "8842986200",
      "HTS_THPR": "1260.53",
      "MRKT_BASIS": "63.32",
      "DPRT": "5.02",
      "NMSC_FCTN_STPL_PRC": "0.00",
      "FMSC_FCTN_STPL_PRC": "0.00",
      "SPEAD_PRC": "3.65",
      "HTS_OTST_STPL_QTY": "195268",
      "OTST_STPL_QTY_ICDC": "-277",
      "OPRC_HOUR": "000000",
      "OPRC_VRSS_PRPR_SIGN": "2",
      "OPRC_VRSS_NMIX_PRPR": "55.65",
      "HGPR_HOUR": "000000",
      "HGPR_VRSS_PRPR_SIGN": "5",
      "HGPR_VRSS_NMIX_PRPR": "-3.60",
      "LWPR_HOUR": "000000",
      "LWPR_VRSS_PRPR_SIGN": "2",
      "LWPR_VRSS_NMIX_PRPR": "56.85",
      "SHNU_RATE": "0.51",
      "CTTR": "103.62",
      "ESDG": "63.32",
      "OTST_STPL_RGBF_QTY_ICDC": "-1",
      "THPR_BASIS": "0.00",
      "FUTS_ASKP1": "1324.25",
      "FUTS_BIDP1": "1323.45",
      "ASKP_RSQN1": "4",
      "BIDP_RSQN1": "1",
      "SELN_CNTG_CSNU": "11268",
      "SHNU_CNTG_CSNU": "10889",
      "NTBY_CNTG_CSNU": "-379",
      "SELN_CNTG_SMTN": "13360",
      "SHNU_CNTG_SMTN": "13844",
      "TOTAL_ASKP_RSQN": "324",
      "TOTAL_BIDP_RSQN": "1003",
      "PRDY_VOL_VRSS_ACML_VOL_RATE": "176.41",
      "DYNM_MXPR": "1349.15",
      "DYNM_LLAM": "1298.55",
      "DYNM_PRC_LIMT_YN": "2"
    }
  }
]