{
  "updated_kst": "2026-06-25 19:23 KST",
  "macro": {
    "us10y": 4.5,
    "us10y_1d_bp": -0.9999999999999787,
    "us10y_5d_bp": 3.000000000000025,
    "us10y_20d_bp": -5.999999999999961,
    "curve_2s10s": 0.33999999999999986,
    "curve_2s10s_1d_bp": 7.000000000000028,
    "curve_2s10s_5d_bp": -5.999999999999961,
    "dxy": 101.58200073242188,
    "dxy_1d": -0.027556222577995726,
    "dxy_5d": 1.4906628525536592,
    "dxy_ma20": 100.03059997558594,
    "gold": 4000.300048828125,
    "gold_1d": 0.2506077206634316,
    "gold_5d": -8.226843046402799,
    "hy_oas": 2.71,
    "hy_oas_1d_bp": 6.000000000000005,
    "hy_oas_5d_bp": 0.0
  },
  "fedwatch": {
    "meeting_date": "2026-07-29",
    "current_range": "350-375",
    "probabilities": {
      "350-375": 66.0,
      "375-400": 34.0
    },
    "ease_prob": 0.0,
    "hold_prob": 66.0,
    "hike_prob": 34.0,
    "zq_ticker": "ZQ=F",
    "zq_price": 96.285,
    "implied_rate": 3.715,
    "dff": 3.63,
    "as_of": "2026-06-25 19:23 KST",
    "source": "ZQ Futures + FRED DFF"
  },
  "us_results": {
    "SPY": {
      "asset": "SPY",
      "total_score": 88,
      "signal": "매수",
      "original_signal": "매수",
      "module_scores": {
        "trend": 30,
        "vix": 25,
        "tactical": 10,
        "breadth": 15,
        "rates": 8
      },
      "module_meta": {
        "trend": {
          "close": 733.239990234375,
          "ma50": 731.242158203125,
          "ma200": 685.9491488647461,
          "ret20": -2.0598534151166747,
          "max_score": 35
        },
        "vix": {
          "vix": 17.950000762939453,
          "vix_5d_chg": -2.6572654930956396,
          "vix_ratio20": 1.0118947363548567,
          "off_10d_high": -7.901482946453409,
          "max_score": 25
        },
        "tactical": {
          "dist20": -1.4666866712175208,
          "ret10": -0.2606353598155309,
          "above_5dma": 0,
          "two_of_three_up": 0,
          "max_score": 15
        },
        "breadth": {
          "bucket": "strong",
          "approx_pct": 65.0,
          "ratio": 0.28691834554136364,
          "ratio_ma20": 0.2805973311819986,
          "ret20": 3.8511639404322118,
          "max_score": 15
        },
        "rates": {
          "dgs10": 4.5,
          "delta20_bp": -5.999999999999961,
          "max_score": 10
        }
      },
      "guardrail_reasons": []
    },
    "QQQ": {
      "asset": "QQQ",
      "total_score": 81,
      "signal": "매수",
      "original_signal": "매수",
      "module_scores": {
        "trend": 24,
        "vix": 25,
        "tactical": 10,
        "breadth": 10,
        "rates": 12
      },
      "module_meta": {
        "trend": {
          "close": 710.6199951171875,
          "ma50": 698.9348278808594,
          "ma200": 629.314946899414,
          "ret20": -2.5851894455166224,
          "max_score": 30
        },
        "vix": {
          "vix": 17.950000762939453,
          "vix_5d_chg": -2.6572654930956396,
          "vix_ratio20": 1.0118947363548567,
          "off_10d_high": -7.901482946453409,
          "max_score": 25
        },
        "tactical": {
          "dist20": -2.144170377763288,
          "ret10": 0.5044907114387653,
          "above_5dma": 0,
          "two_of_three_up": 0,
          "max_score": 15
        },
        "breadth": {
          "bucket": "strong",
          "approx_pct": 65.0,
          "ratio": 0.21572711731320943,
          "ratio_ma20": 0.21338234279676174,
          "ret20": 3.165253645077848,
          "max_score": 10
        },
        "rates": {
          "dgs10": 4.5,
          "delta20_bp": -5.999999999999961,
          "max_score": 20
        }
      },
      "guardrail_reasons": []
    }
  },
  "kr_results": {
    "KOSPI": {
      "asset": "KOSPI",
      "total_score": 97,
      "signal": "보유",
      "original_signal": "매수",
      "module_scores": {
        "trend": 40,
        "vkospi": 8,
        "tactical": 17,
        "leadership": 6,
        "turnover": 10,
        "flow": 0,
        "fx": 8,
        "oil": 8
      },
      "module_meta": {
        "trend": {
          "close": 8930.2998046875,
          "ma50": 7601.2412109375,
          "ma200": 5255.722509765625,
          "ret20": 8.52625071666444,
          "max_score": 40
        },
        "vkospi": {
          "vkospi": 55.64,
          "vkospi_5d_chg": -8.426596445029622,
          "vkospi_ratio20": 0.9456473707467963,
          "off_10d_high": -22.528543581175153,
          "max_score": 27
        },
        "tactical": {
          "dist20": 5.544234527308345,
          "ret10": 15.022631264162234,
          "above_5dma": 1,
          "two_of_three_up": 1,
          "max_score": 17
        },
        "leadership": {
          "bucket": "kosdaq_weak",
          "approx_pct": 28.0,
          "rel": 0.09941547506530338,
          "rel_ma20": 0.1177314107146332,
          "rel_ret20": -27.805270749003764,
          "max_score": 6
        },
        "turnover": {
          "current": 34.025853798776,
          "ma20_ratio": 0.9979194873193801,
          "chg5": 43.449910153167615,
          "max_score": 12
        },
        "flow": {
          "foreign_1d_bil": -8753.6,
          "foreign_5d_bil": -126367.5,
          "foreign_20d_bil": -363866.7,
          "foreign_5d_ratio": -7.43,
          "max_score": 20
        },
        "fx": {
          "usdkrw": 1541.949951171875,
          "usdkrw_ret20": 2.5839736412387904,
          "max_score": 20
        },
        "oil": {
          "wti": 69.54000091552734,
          "wti_ret20": -21.583219805798016,
          "max_score": 10
        }
      },
      "guardrail_reasons": [
        "외국인 1일 순매도 → 매수 제한",
        "5일·20일 누적 수급 동반 부진 → 매수 제한",
        "원/달러 급등 + 단기 수급 약세 → 매수 제한"
      ]
    },
    "KOSDAQ": {
      "asset": "KOSDAQ",
      "total_score": 51,
      "signal": "보유",
      "original_signal": "보유",
      "module_scores": {
        "trend": 0,
        "vkospi": 8,
        "tactical": 0,
        "leadership": 1,
        "turnover": 8,
        "flow": 18,
        "fx": 8,
        "oil": 8
      },
      "module_meta": {
        "trend": {
          "close": 887.8099975585938,
          "ma50": 1097.753203125,
          "ma200": 1001.5642514038086,
          "ret20": -21.649767128846754,
          "max_score": 36
        },
        "vkospi": {
          "vkospi": 55.64,
          "vkospi_5d_chg": -8.426596445029622,
          "vkospi_ratio20": 0.9456473707467963,
          "off_10d_high": -22.528543581175153,
          "max_score": 27
        },
        "tactical": {
          "dist20": -10.653572160831793,
          "ret10": -10.945602591843695,
          "above_5dma": 0,
          "two_of_three_up": 0,
          "max_score": 17
        },
        "leadership": {
          "bucket": "weak",
          "approx_pct": 28.0,
          "rel": 0.09941547506530338,
          "rel_ma20": 0.1177314107146332,
          "rel_ret20": -27.805270749003764,
          "max_score": 12
        },
        "turnover": {
          "current": 14.143306243848,
          "ma20_ratio": 0.9766744459812186,
          "chg5": -1.7616748107015967,
          "max_score": 12
        },
        "flow": {
          "foreign_1d_bil": 212.4,
          "foreign_5d_bil": 10766.8,
          "foreign_20d_bil": 18462.1,
          "foreign_5d_ratio": 1.52,
          "max_score": 18
        },
        "fx": {
          "usdkrw": 1541.949951171875,
          "usdkrw_ret20": 2.5839736412387904,
          "max_score": 20
        },
        "oil": {
          "wti": 69.54000091552734,
          "wti_ret20": -21.583219805798016,
          "max_score": 10
        }
      },
      "guardrail_reasons": [
        "코스닥 리더십 약세 → 매수 제한"
      ]
    }
  }
}