{
  "updated_kst": "2026-07-14 18:22 KST",
  "macro": {
    "us10y": 4.56,
    "us10y_1d_bp": 1.9999999999999574,
    "us10y_5d_bp": 6.99999999999994,
    "us10y_20d_bp": 0.9999999999999787,
    "curve_2s10s": 0.34999999999999964,
    "curve_2s10s_1d_bp": -3.000000000000025,
    "curve_2s10s_5d_bp": -8.881784197001252e-14,
    "dxy": 101.06500244140625,
    "dxy_1d": -0.21227916714250394,
    "dxy_5d": -0.07415162022421651,
    "dxy_ma20": 100.93925018310547,
    "gold": 4029.39990234375,
    "gold_1d": 0.8106055127282907,
    "gold_5d": -2.7959353437522316,
    "hy_oas": 2.69,
    "hy_oas_1d_bp": -1.000000000000023,
    "hy_oas_5d_bp": -5.000000000000027
  },
  "fedwatch": {
    "meeting_date": "2026-07-29",
    "current_range": "350-375",
    "probabilities": {
      "350-375": 56.0,
      "375-400": 44.0
    },
    "ease_prob": 0.0,
    "hold_prob": 56.0,
    "hike_prob": 44.0,
    "zq_ticker": "ZQ=F",
    "zq_price": 96.27,
    "implied_rate": 3.73,
    "dff": 3.62,
    "as_of": "2026-07-14 18:22 KST",
    "source": "ZQ Futures + FRED DFF"
  },
  "us_results": {
    "SPY": {
      "asset": "SPY",
      "total_score": 95,
      "signal": "매수",
      "original_signal": "매수",
      "module_scores": {
        "trend": 35,
        "vix": 25,
        "tactical": 12,
        "breadth": 15,
        "rates": 8
      },
      "module_meta": {
        "trend": {
          "close": 749.1699829101562,
          "ma50": 740.6941333007812,
          "ma200": 691.5513775634765,
          "ret20": 1.8081765701204233,
          "max_score": 35
        },
        "vix": {
          "vix": 17.360000610351562,
          "vix_5d_chg": 7.625551851091994,
          "vix_ratio20": 1.018241579107913,
          "off_10d_high": 0.0,
          "max_score": 25
        },
        "tactical": {
          "dist20": 0.695143778886198,
          "ret10": 2.7682125881170583,
          "above_5dma": 0,
          "two_of_three_up": 1,
          "max_score": 15
        },
        "breadth": {
          "bucket": "strong",
          "approx_pct": 65.0,
          "ratio": 0.28595645930094676,
          "ratio_ma20": 0.28499816036294445,
          "ret20": 0.7104052696713437,
          "max_score": 15
        },
        "rates": {
          "dgs10": 4.56,
          "delta20_bp": 0.9999999999999787,
          "max_score": 10
        }
      },
      "guardrail_reasons": []
    },
    "QQQ": {
      "asset": "QQQ",
      "total_score": 71,
      "signal": "매수",
      "original_signal": "매수",
      "module_scores": {
        "trend": 12,
        "vix": 25,
        "tactical": 12,
        "breadth": 10,
        "rates": 12
      },
      "module_meta": {
        "trend": {
          "close": 711.739990234375,
          "ma50": 715.6094836425781,
          "ma200": 637.2107650756836,
          "ret20": -0.6411508268807542,
          "max_score": 30
        },
        "vix": {
          "vix": 17.360000610351562,
          "vix_5d_chg": 7.625551851091994,
          "vix_ratio20": 1.018241579107913,
          "off_10d_high": 0.0,
          "max_score": 25
        },
        "tactical": {
          "dist20": -1.4340516846698237,
          "ret10": 0.7388284208263762,
          "above_5dma": 0,
          "two_of_three_up": 1,
          "max_score": 15
        },
        "breadth": {
          "bucket": "strong",
          "approx_pct": 65.0,
          "ratio": 0.22054402362443218,
          "ratio_ma20": 0.21711569465502767,
          "ret20": 3.4122573384542054,
          "max_score": 10
        },
        "rates": {
          "dgs10": 4.56,
          "delta20_bp": 0.9999999999999787,
          "max_score": 20
        }
      },
      "guardrail_reasons": []
    }
  },
  "kr_results": {
    "KOSPI": {
      "asset": "KOSPI",
      "total_score": 67,
      "signal": "보유",
      "original_signal": "보유",
      "module_scores": {
        "trend": 16,
        "vkospi": 8,
        "tactical": 2,
        "leadership": 3,
        "turnover": 10,
        "flow": 5,
        "fx": 15,
        "oil": 8
      },
      "module_meta": {
        "trend": {
          "close": 6856.830078125,
          "ma50": 7971.2134375,
          "ma200": 5548.117613525391,
          "ret20": -21.426095099416543,
          "max_score": 40
        },
        "vkospi": {
          "vkospi": 55.64,
          "vkospi_5d_chg": -8.426596445029622,
          "vkospi_ratio20": 0.9456473707467963,
          "off_10d_high": -22.528543581175153,
          "max_score": 27
        },
        "tactical": {
          "dist20": -15.560663067753644,
          "ret10": -19.107581225440427,
          "above_5dma": 0,
          "two_of_three_up": 1,
          "max_score": 17
        },
        "leadership": {
          "bucket": "neutral",
          "approx_pct": 50.0,
          "rel": 0.11433562907878407,
          "rel_ma20": 0.10908288403065543,
          "rel_ret20": -2.053514034792392,
          "max_score": 6
        },
        "turnover": {
          "current": 34.025853798776,
          "ma20_ratio": 0.9979194873193801,
          "chg5": 43.449910153167615,
          "max_score": 12
        },
        "flow": {
          "foreign_1d_bil": 9565.1,
          "foreign_5d_bil": -5588.2,
          "foreign_20d_bil": -412161.0,
          "foreign_5d_ratio": -0.33,
          "max_score": 20
        },
        "fx": {
          "usdkrw": 1494.8499755859375,
          "usdkrw_ret20": -1.2198480346431229,
          "max_score": 20
        },
        "oil": {
          "wti": 80.33999633789062,
          "wti_ret20": -5.348728867147234,
          "max_score": 10
        }
      },
      "guardrail_reasons": [
        "5일·20일 누적 수급 동반 부진 → 매수 제한"
      ]
    },
    "KOSDAQ": {
      "asset": "KOSDAQ",
      "total_score": 51,
      "signal": "보유",
      "original_signal": "보유",
      "module_scores": {
        "trend": 0,
        "vkospi": 8,
        "tactical": 0,
        "leadership": 6,
        "turnover": 8,
        "flow": 6,
        "fx": 15,
        "oil": 8
      },
      "module_meta": {
        "trend": {
          "close": 783.97998046875,
          "ma50": 1012.7199987792969,
          "ma200": 1003.723000793457,
          "ret20": -23.039621264234455,
          "max_score": 36
        },
        "vkospi": {
          "vkospi": 55.64,
          "vkospi_5d_chg": -8.426596445029622,
          "vkospi_ratio20": 0.9456473707467963,
          "off_10d_high": -22.528543581175153,
          "max_score": 27
        },
        "tactical": {
          "dist20": -11.35053269951084,
          "ret10": -14.429480371092795,
          "above_5dma": 0,
          "two_of_three_up": 0,
          "max_score": 17
        },
        "leadership": {
          "bucket": "neutral",
          "approx_pct": 50.0,
          "rel": 0.11433562907878407,
          "rel_ma20": 0.10908288403065543,
          "rel_ret20": -2.053514034792392,
          "max_score": 12
        },
        "turnover": {
          "current": 14.143306243848,
          "ma20_ratio": 0.9766744459812186,
          "chg5": -1.7616748107015967,
          "max_score": 12
        },
        "flow": {
          "foreign_1d_bil": -2471.0,
          "foreign_5d_bil": -4315.2,
          "foreign_20d_bil": 10551.7,
          "foreign_5d_ratio": -0.61,
          "max_score": 18
        },
        "fx": {
          "usdkrw": 1494.8499755859375,
          "usdkrw_ret20": -1.2198480346431229,
          "max_score": 20
        },
        "oil": {
          "wti": 80.33999633789062,
          "wti_ret20": -5.348728867147234,
          "max_score": 10
        }
      },
      "guardrail_reasons": []
    }
  }
}