{
  "updated_kst": "2026-07-09 08:05 KST",
  "macro": {
    "us10y": 4.55,
    "us10y_1d_bp": 6.99999999999994,
    "us10y_5d_bp": 16.999999999999993,
    "us10y_20d_bp": 0.0,
    "curve_2s10s": 0.35999999999999943,
    "curve_2s10s_1d_bp": 0.9999999999998899,
    "curve_2s10s_5d_bp": 7.999999999999918,
    "dxy": 101.06600189208984,
    "dxy_1d": -0.07316343484787824,
    "dxy_5d": -0.12254229303750863,
    "dxy_ma20": 100.7007999420166,
    "gold": 4087.60009765625,
    "gold_1d": -1.3919308554233734,
    "gold_5d": 1.6082974193517785,
    "hy_oas": 2.67,
    "hy_oas_1d_bp": -5.000000000000027,
    "hy_oas_5d_bp": -8.000000000000007
  },
  "fedwatch": {
    "meeting_date": "2026-07-29",
    "current_range": "350-375",
    "probabilities": {
      "350-375": 72.0,
      "375-400": 28.0
    },
    "ease_prob": 0.0,
    "hold_prob": 72.0,
    "hike_prob": 28.0,
    "zq_ticker": "ZQ=F",
    "zq_price": 96.3,
    "implied_rate": 3.7,
    "dff": 3.63,
    "as_of": "2026-07-09 08:05 KST",
    "source": "ZQ Futures + FRED DFF"
  },
  "us_results": {
    "SPY": {
      "asset": "SPY",
      "total_score": 83,
      "signal": "매수",
      "original_signal": "매수",
      "module_scores": {
        "trend": 35,
        "vix": 25,
        "tactical": 10,
        "breadth": 5,
        "rates": 8
      },
      "module_meta": {
        "trend": {
          "close": 745.4000244140625,
          "ma50": 738.2364331054688,
          "ma200": 690.159066772461,
          "ret20": 1.0958044107998388,
          "max_score": 35
        },
        "vix": {
          "vix": 16.899999618530273,
          "vix_5d_chg": 2.735555226262565,
          "vix_ratio20": 0.9526493604775064,
          "off_10d_high": -10.534673559643771,
          "max_score": 25
        },
        "tactical": {
          "dist20": 0.6024929670876533,
          "ret10": 1.6112771679781313,
          "above_5dma": 0,
          "two_of_three_up": 0,
          "max_score": 15
        },
        "breadth": {
          "bucket": "weak",
          "approx_pct": 35.0,
          "ratio": 0.2846793533647205,
          "ratio_ma20": 0.28489268007321933,
          "ret20": 1.494536874928687,
          "max_score": 15
        },
        "rates": {
          "dgs10": 4.55,
          "delta20_bp": 0.0,
          "max_score": 10
        }
      },
      "guardrail_reasons": []
    },
    "QQQ": {
      "asset": "QQQ",
      "total_score": 71,
      "signal": "매수",
      "original_signal": "매수",
      "module_scores": {
        "trend": 12,
        "vix": 25,
        "tactical": 12,
        "breadth": 10,
        "rates": 12
      },
      "module_meta": {
        "trend": {
          "close": 711.4400024414062,
          "ma50": 712.0223388671875,
          "ma200": 635.3706622314453,
          "ret20": -0.537399613557632,
          "max_score": 30
        },
        "vix": {
          "vix": 16.899999618530273,
          "vix_5d_chg": 2.735555226262565,
          "vix_ratio20": 0.9526493604775064,
          "off_10d_high": -10.534673559643771,
          "max_score": 25
        },
        "tactical": {
          "dist20": -1.1730241815559705,
          "ret10": -0.30967867961201323,
          "above_5dma": 0,
          "two_of_three_up": 1,
          "max_score": 15
        },
        "breadth": {
          "bucket": "strong",
          "approx_pct": 65.0,
          "ratio": 0.22065106711576543,
          "ratio_ma20": 0.21619550383584962,
          "ret20": 3.0882804553710397,
          "max_score": 10
        },
        "rates": {
          "dgs10": 4.55,
          "delta20_bp": 0.0,
          "max_score": 20
        }
      },
      "guardrail_reasons": []
    }
  },
  "kr_results": {
    "KOSPI": {
      "asset": "KOSPI",
      "total_score": 63,
      "signal": "보유",
      "original_signal": "보유",
      "module_scores": {
        "trend": 16,
        "vkospi": 8,
        "tactical": 0,
        "leadership": 6,
        "turnover": 10,
        "flow": 0,
        "fx": 15,
        "oil": 8
      },
      "module_meta": {
        "trend": {
          "close": 7656.31005859375,
          "ma50": 7915.61322265625,
          "ma200": 5453.333762207031,
          "ret20": -5.441816930883759,
          "max_score": 40
        },
        "vkospi": {
          "vkospi": 55.64,
          "vkospi_5d_chg": -8.426596445029622,
          "vkospi_ratio20": 0.9456473707467963,
          "off_10d_high": -22.528543581175153,
          "max_score": 27
        },
        "tactical": {
          "dist20": -8.647364487817743,
          "ret10": -6.674067212238166,
          "above_5dma": 0,
          "two_of_three_up": 0,
          "max_score": 17
        },
        "leadership": {
          "bucket": "kosdaq_weak",
          "approx_pct": 28.0,
          "rel": 0.1085679621263175,
          "rel_ma20": 0.11182818757779048,
          "rel_ret20": -9.169443291431278,
          "max_score": 6
        },
        "turnover": {
          "current": 34.025853798776,
          "ma20_ratio": 0.9979194873193801,
          "chg5": 43.449910153167615,
          "max_score": 12
        },
        "flow": {
          "foreign_1d_bil": 0.0,
          "foreign_5d_bil": -60629.3,
          "foreign_20d_bil": -354967.6,
          "foreign_5d_ratio": -3.56,
          "max_score": 20
        },
        "fx": {
          "usdkrw": 1504.5400390625,
          "usdkrw_ret20": -1.344874535847873,
          "max_score": 20
        },
        "oil": {
          "wti": 74.5999984741211,
          "wti_ret20": -18.291351609451223,
          "max_score": 10
        }
      },
      "guardrail_reasons": [
        "5일·20일 누적 수급 동반 부진 → 매수 제한"
      ]
    },
    "KOSDAQ": {
      "asset": "KOSDAQ",
      "total_score": 55,
      "signal": "보유",
      "original_signal": "보유",
      "module_scores": {
        "trend": 0,
        "vkospi": 8,
        "tactical": 0,
        "leadership": 1,
        "turnover": 8,
        "flow": 15,
        "fx": 15,
        "oil": 8
      },
      "module_meta": {
        "trend": {
          "close": 831.22998046875,
          "ma50": 1053.5280004882814,
          "ma200": 1004.685901184082,
          "ret20": -14.112275904814142,
          "max_score": 36
        },
        "vkospi": {
          "vkospi": 55.64,
          "vkospi_5d_chg": -8.426596445029622,
          "vkospi_ratio20": 0.9456473707467963,
          "off_10d_high": -22.528543581175153,
          "max_score": 27
        },
        "tactical": {
          "dist20": -11.182655501953931,
          "ret10": -6.762611914671279,
          "above_5dma": 0,
          "two_of_three_up": 0,
          "max_score": 17
        },
        "leadership": {
          "bucket": "weak",
          "approx_pct": 28.0,
          "rel": 0.1085679621263175,
          "rel_ma20": 0.11182818757779048,
          "rel_ret20": -9.169443291431278,
          "max_score": 12
        },
        "turnover": {
          "current": 14.143306243848,
          "ma20_ratio": 0.9766744459812186,
          "chg5": -1.7616748107015967,
          "max_score": 12
        },
        "flow": {
          "foreign_1d_bil": 0.0,
          "foreign_5d_bil": 6468.7,
          "foreign_20d_bil": 9753.2,
          "foreign_5d_ratio": 0.91,
          "max_score": 18
        },
        "fx": {
          "usdkrw": 1504.5400390625,
          "usdkrw_ret20": -1.344874535847873,
          "max_score": 20
        },
        "oil": {
          "wti": 74.5999984741211,
          "wti_ret20": -18.291351609451223,
          "max_score": 10
        }
      },
      "guardrail_reasons": [
        "코스닥 리더십 약세 → 매수 제한"
      ]
    }
  }
}